{
    "dados": [
        {
            "ano": 2024,
            "mes": 3,
            "tipoDespesa": "MANUTENÇÃO DE ESCRITÓRIO DE APOIO À ATIVIDADE PARLAMENTAR",
            "codDocumento": 7703443,
            "tipoDocumento": "Nota Fiscal",
            "codTipoDocumento": 0,
            "dataDocumento": "2024-03-13",
            "numDocumento": "1094",
            "valorDocumento": 720.0,
            "urlDocumento": "https://www.camara.leg.br/cota-parlamentar/documentos/publ/3556/2024/7703443.pdf",
            "nomeFornecedor": "AMORETTO CAFES EXPRESSO LTDA",
            "cnpjCpfFornecedor": "08532429000131",
            "valorLiquido": 720.0,
            "valorGlosa": 0.0,
            "numRessarcimento": "",
            "codLote": 2022056,
            "parcela": 0
        },
        {
            "ano": 2024,
            "mes": 4,
            "tipoDespesa": "MANUTENÇÃO DE ESCRITÓRIO DE APOIO À ATIVIDADE PARLAMENTAR",
            "codDocumento": 7721466,
            "tipoDocumento": "Nota Fiscal",
            "codTipoDocumento": 0,
            "dataDocumento": "2024-04-04",
            "numDocumento": "1178",
            "valorDocumento": 720.0,
            "urlDocumento": "https://www.camara.leg.br/cota-parlamentar/documentos/publ/3556/2024/7721466.pdf",
            "nomeFornecedor": "AMORETTO CAFES EXPRESSO LTDA",
            "cnpjCpfFornecedor": "08532429000131",
            "valorLiquido": 720.0,
            "valorGlosa": 0.0,
            "numRessarcimento": "",
            "codLote": 2031651,
            "parcela": 0
        },
        {
            "ano": 2024,
            "mes": 5,
            "tipoDespesa": "MANUTENÇÃO DE ESCRITÓRIO DE APOIO À ATIVIDADE PARLAMENTAR",
            "codDocumento": 7741025,
            "tipoDocumento": "Nota Fiscal",
            "codTipoDocumento": 0,
            "dataDocumento": "2024-05-08",
            "numDocumento": "1267",
            "valorDocumento": 720.0,
            "urlDocumento": "https://www.camara.leg.br/cota-parlamentar/documentos/publ/3556/2024/7741025.pdf",
            "nomeFornecedor": "AMORETTO CAFES EXPRESSO LTDA",
            "cnpjCpfFornecedor": "08532429000131",
            "valorLiquido": 720.0,
            "valorGlosa": 0.0,
            "numRessarcimento": "",
            "codLote": 2042305,
            "parcela": 0
        },
        {
            "ano": 2024,
            "mes": 6,
            "tipoDespesa": "MANUTENÇÃO DE ESCRITÓRIO DE APOIO À ATIVIDADE PARLAMENTAR",
            "codDocumento": 7755854,
            "tipoDocumento": "Nota Fiscal",
            "codTipoDocumento": 0,
            "dataDocumento": "2024-06-10",
            "numDocumento": "1356",
            "valorDocumento": 720.0,
            "urlDocumento": "https://www.camara.leg.br/cota-parlamentar/documentos/publ/3556/2024/7755854.pdf",
            "nomeFornecedor": "AMORETTO CAFES EXPRESSO LTDA",
            "cnpjCpfFornecedor": "08532429000131",
            "valorLiquido": 720.0,
            "valorGlosa": 0.0,
            "numRessarcimento": "",
            "codLote": 2050116,
            "parcela": 0
        },
        {
            "ano": 2024,
            "mes": 7,
            "tipoDespesa": "MANUTENÇÃO DE ESCRITÓRIO DE APOIO À ATIVIDADE PARLAMENTAR",
            "codDocumento": 7777162,
            "tipoDocumento": "Nota Fiscal",
            "codTipoDocumento": 0,
            "dataDocumento": "2024-07-10",
            "numDocumento": "1435",
            "valorDocumento": 720.0,
            "urlDocumento": "https://www.camara.leg.br/cota-parlamentar/documentos/publ/3556/2024/7777162.pdf",
            "nomeFornecedor": "AMORETTO CAFES EXPRESSO LTDA",
            "cnpjCpfFornecedor": "08532429000131",
            "valorLiquido": 720.0,
            "valorGlosa": 0.0,
            "numRessarcimento": "",
            "codLote": 2060985,
            "parcela": 0
        },
        {
            "ano": 2024,
            "mes": 3,
            "tipoDespesa": "MANUTENÇÃO DE ESCRITÓRIO DE APOIO À ATIVIDADE PARLAMENTAR",
            "codDocumento": 7721464,
            "tipoDocumento": "Nota Fiscal",
            "codTipoDocumento": 0,
            "dataDocumento": "2024-03-27",
            "numDocumento": "134480973",
            "valorDocumento": 1246.55,
            "urlDocumento": "https://www.camara.leg.br/cota-parlamentar/documentos/publ/3556/2024/7721464.pdf",
            "nomeFornecedor": "CEMIG DISTRIBUIÇÃO S.A.",
            "cnpjCpfFornecedor": "06981180000116",
            "valorLiquido": 1246.55,
            "valorGlosa": 0.0,
            "numRessarcimento": "",
            "codLote": 2031649,
            "parcela": 0
        },
        {
            "ano": 2024,
            "mes": 4,
            "tipoDespesa": "MANUTENÇÃO DE ESCRITÓRIO DE APOIO À ATIVIDADE PARLAMENTAR",
            "codDocumento": 7737213,
            "tipoDocumento": "Nota Fiscal",
            "codTipoDocumento": 0,
            "dataDocumento": "2024-04-26",
            "numDocumento": "144376996",
            "valorDocumento": 688.53,
            "urlDocumento": "https://www.camara.leg.br/cota-parlamentar/documentos/publ/3556/2024/7737213.pdf",
            "nomeFornecedor": "CEMIG DISTRIBUIÇÃO S.A.",
            "cnpjCpfFornecedor": "06981180000116",
            "valorLiquido": 688.53,
            "valorGlosa": 0.0,
            "numRessarcimento": "",
            "codLote": 2040385,
            "parcela": 0
        },
        {
            "ano": 2024,
            "mes": 5,
            "tipoDespesa": "MANUTENÇÃO DE ESCRITÓRIO DE APOIO À ATIVIDADE PARLAMENTAR",
            "codDocumento": 7757827,
            "tipoDocumento": "Nota Fiscal",
            "codTipoDocumento": 0,
            "dataDocumento": "2024-05-27",
            "numDocumento": "154259511",
            "valorDocumento": 568.89,
            "urlDocumento": "https://www.camara.leg.br/cota-parlamentar/documentos/publ/3556/2024/7757827.pdf",
            "nomeFornecedor": "CEMIG DISTRIBUIÇÃO S.A.",
            "cnpjCpfFornecedor": "06981180000116",
            "valorLiquido": 568.89,
            "valorGlosa": 0.0,
            "numRessarcimento": "",
            "codLote": 2051155,
            "parcela": 0
        },
        {
            "ano": 2024,
            "mes": 6,
            "tipoDespesa": "MANUTENÇÃO DE ESCRITÓRIO DE APOIO À ATIVIDADE PARLAMENTAR",
            "codDocumento": 7774659,
            "tipoDocumento": "Nota Fiscal",
            "codTipoDocumento": 0,
            "dataDocumento": "2024-06-28",
            "numDocumento": "164066058",
            "valorDocumento": 169.96,
            "urlDocumento": "https://www.camara.leg.br/cota-parlamentar/documentos/publ/3556/2024/7774659.pdf",
            "nomeFornecedor": "CEMIG DISTRIBUIÇÃO S.A.",
            "cnpjCpfFornecedor": "06981180000116",
            "valorLiquido": 169.96,
            "valorGlosa": 0.0,
            "numRessarcimento": "",
            "codLote": 2059759,
            "parcela": 0
        },
        {
            "ano": 2024,
            "mes": 5,
            "tipoDespesa": "MANUTENÇÃO DE ESCRITÓRIO DE APOIO À ATIVIDADE PARLAMENTAR",
            "codDocumento": 7757828,
            "tipoDocumento": "Nota Fiscal",
            "codTipoDocumento": 0,
            "dataDocumento": "2024-05-29",
            "numDocumento": "001.24.35071672-6",
            "valorDocumento": 59.84,
            "urlDocumento": "https://www.camara.leg.br/cota-parlamentar/documentos/publ/3556/2024/7757828.pdf",
            "nomeFornecedor": "COPASA",
            "cnpjCpfFornecedor": "17281106000103",
            "valorLiquido": 59.84,
            "valorGlosa": 0.0,
            "numRessarcimento": "",
            "codLote": 2051157,
            "parcela": 0
        },
        {
            "ano": 2024,
            "mes": 3,
            "tipoDespesa": "MANUTENÇÃO DE ESCRITÓRIO DE APOIO À ATIVIDADE PARLAMENTAR",
            "codDocumento": 7710360,
            "tipoDocumento": "Nota Fiscal",
            "codTipoDocumento": 0,
            "dataDocumento": "2024-03-13",
            "numDocumento": "00124151790519",
            "valorDocumento": 76.4,
            "urlDocumento": "https://www.camara.leg.br/cota-parlamentar/documentos/publ/3556/2024/7710360.pdf",
            "nomeFornecedor": "COPASA",
            "cnpjCpfFornecedor": "17281106000103",
            "valorLiquido": 76.4,
            "valorGlosa": 0.0,
            "numRessarcimento": "",
            "codLote": 2025708,
            "parcela": 0
        },
        {
            "ano": 2024,
            "mes": 3,
            "tipoDespesa": "MANUTENÇÃO DE ESCRITÓRIO DE APOIO À ATIVIDADE PARLAMENTAR",
            "codDocumento": 7721463,
            "tipoDocumento": "Nota Fiscal",
            "codTipoDocumento": 0,
            "dataDocumento": "2024-03-28",
            "numDocumento": "00124209885053",
            "valorDocumento": 69.64,
            "urlDocumento": "https://www.camara.leg.br/cota-parlamentar/documentos/publ/3556/2024/7721463.pdf",
            "nomeFornecedor": "COPASA",
            "cnpjCpfFornecedor": "17281106000103",
            "valorLiquido": 68.12,
            "valorGlosa": 1.52,
            "numRessarcimento": "",
            "codLote": 2031649,
            "parcela": 0
        },
        {
            "ano": 2024,
            "mes": 4,
            "tipoDespesa": "MANUTENÇÃO DE ESCRITÓRIO DE APOIO À ATIVIDADE PARLAMENTAR",
            "codDocumento": 7737212,
            "tipoDocumento": "Nota Fiscal",
            "codTipoDocumento": 0,
            "dataDocumento": "2024-04-29",
            "numDocumento": "00124278496382",
            "valorDocumento": 69.77,
            "urlDocumento": "https://www.camara.leg.br/cota-parlamentar/documentos/publ/3556/2024/7737212.pdf",
            "nomeFornecedor": "COPASA",
            "cnpjCpfFornecedor": "17281106000103",
            "valorLiquido": 68.12,
            "valorGlosa": 1.65,
            "numRessarcimento": "",
            "codLote": 2040385,
            "parcela": 0
        },
        {
            "ano": 2024,
            "mes": 6,
            "tipoDespesa": "MANUTENÇÃO DE ESCRITÓRIO DE APOIO À ATIVIDADE PARLAMENTAR",
            "codDocumento": 7774664,
            "tipoDocumento": "Nota Fiscal",
            "codTipoDocumento": 0,
            "dataDocumento": "2024-07-01",
            "numDocumento": "00124420890142",
            "valorDocumento": 68.12,
            "urlDocumento": "https://www.camara.leg.br/cota-parlamentar/documentos/publ/3556/2024/7774664.pdf",
            "nomeFornecedor": "COPASA",
            "cnpjCpfFornecedor": "17281106000103",
            "valorLiquido": 68.12,
            "valorGlosa": 0.0,
            "numRessarcimento": "",
            "codLote": 2059759,
            "parcela": 0
        },
        {
            "ano": 2024,
            "mes": 3,
            "tipoDespesa": "MANUTENÇÃO DE ESCRITÓRIO DE APOIO À ATIVIDADE PARLAMENTAR",
            "codDocumento": 7710309,
            "tipoDocumento": "Nota Fiscal",
            "codTipoDocumento": 0,
            "dataDocumento": "2024-03-04",
            "numDocumento": "000010095",
            "valorDocumento": 49.96,
            "urlDocumento": "https://www.camara.leg.br/cota-parlamentar/documentos/publ/3556/2024/7710309.pdf",
            "nomeFornecedor": "CVS TELECOMUNICACOES LTDA",
            "cnpjCpfFornecedor": "46479229000151",
            "valorLiquido": 49.96,
            "valorGlosa": 0.0,
            "numRessarcimento": "",
            "codLote": 2025678,
            "parcela": 0
        }
    ],
    "links": [
        {
            "rel": "self",
            "href": "https://dadosabertos.camara.leg.br/api/v2/deputados/220626/despesas?ordem=ASC&ordenarPor=ano"
        },
        {
            "rel": "next",
            "href": "https://dadosabertos.camara.leg.br/api/v2/deputados/220626/despesas?ordem=ASC&ordenarPor=ano&pagina=2&itens=15"
        },
        {
            "rel": "first",
            "href": "https://dadosabertos.camara.leg.br/api/v2/deputados/220626/despesas?ordem=ASC&ordenarPor=ano&pagina=1&itens=15"
        },
        {
            "rel": "last",
            "href": "https://dadosabertos.camara.leg.br/api/v2/deputados/220626/despesas?ordem=ASC&ordenarPor=ano&pagina=9&itens=15"
        }
    ]
}