{
    "dados": [
        {
            "ano": 2024,
            "mes": 6,
            "tipoDespesa": "MANUTENÇÃO DE ESCRITÓRIO DE APOIO À ATIVIDADE PARLAMENTAR",
            "codDocumento": 7783873,
            "tipoDocumento": "Nota Fiscal",
            "codTipoDocumento": 0,
            "dataDocumento": "2024-06-03",
            "numDocumento": "202406899631",
            "valorDocumento": 358.6,
            "urlDocumento": "https://www.camara.leg.br/cota-parlamentar/documentos/publ/3516/2024/7783873.pdf",
            "nomeFornecedor": "Companhia de Saneamento Ambiental do Maranhão - CAEMA",
            "cnpjCpfFornecedor": "06274757000150",
            "valorLiquido": 358.6,
            "valorGlosa": 0.0,
            "numRessarcimento": "",
            "codLote": 2064314,
            "parcela": 0
        },
        {
            "ano": 2024,
            "mes": 7,
            "tipoDespesa": "MANUTENÇÃO DE ESCRITÓRIO DE APOIO À ATIVIDADE PARLAMENTAR",
            "codDocumento": 7783882,
            "tipoDocumento": "Recibos/Outros",
            "codTipoDocumento": 1,
            "dataDocumento": "2024-07-01",
            "numDocumento": "202407899631",
            "valorDocumento": 209.0,
            "urlDocumento": "https://www.camara.leg.br/cota-parlamentar/documentos/publ/3516/2024/7783882.pdf",
            "nomeFornecedor": "Companhia de Saneamento Ambiental do Maranhão - CAEMA",
            "cnpjCpfFornecedor": "06274757000150",
            "valorLiquido": 209.0,
            "valorGlosa": 0.0,
            "numRessarcimento": "",
            "codLote": 2064318,
            "parcela": 0
        },
        {
            "ano": 2024,
            "mes": 3,
            "tipoDespesa": "MANUTENÇÃO DE ESCRITÓRIO DE APOIO À ATIVIDADE PARLAMENTAR",
            "codDocumento": 7751044,
            "tipoDocumento": "Nota Fiscal",
            "codTipoDocumento": 0,
            "dataDocumento": "2024-03-27",
            "numDocumento": "078362010",
            "valorDocumento": 1082.24,
            "urlDocumento": "https://www.camara.leg.br/cota-parlamentar/documentos/publ/3516/2024/7751044.pdf",
            "nomeFornecedor": "EQUATORIAL MARANHÃO DISTRIBUIDORA DE ENERGIA S.A",
            "cnpjCpfFornecedor": "06272793000184",
            "valorLiquido": 1049.25,
            "valorGlosa": 32.99,
            "numRessarcimento": "",
            "codLote": 2047684,
            "parcela": 0
        },
        {
            "ano": 2024,
            "mes": 6,
            "tipoDespesa": "MANUTENÇÃO DE ESCRITÓRIO DE APOIO À ATIVIDADE PARLAMENTAR",
            "codDocumento": 7783853,
            "tipoDocumento": "Nota Fiscal",
            "codTipoDocumento": 0,
            "dataDocumento": "2024-06-27",
            "numDocumento": "3017411445",
            "valorDocumento": 1043.39,
            "urlDocumento": "https://www.camara.leg.br/cota-parlamentar/documentos/publ/3516/2024/7783853.pdf",
            "nomeFornecedor": "EQUATORIAL MARANHÃO DISTRIBUIDORA DE ENERGIA S.A",
            "cnpjCpfFornecedor": "06272793000184",
            "valorLiquido": 997.64,
            "valorGlosa": 45.75,
            "numRessarcimento": "",
            "codLote": 2064314,
            "parcela": 0
        },
        {
            "ano": 2024,
            "mes": 4,
            "tipoDespesa": "MANUTENÇÃO DE ESCRITÓRIO DE APOIO À ATIVIDADE PARLAMENTAR",
            "codDocumento": 7760264,
            "tipoDocumento": "Recibos/Outros",
            "codTipoDocumento": 1,
            "dataDocumento": "2024-04-10",
            "numDocumento": "-",
            "valorDocumento": 3300.0,
            "urlDocumento": "https://www.camara.leg.br/cota-parlamentar/documentos/publ/3516/2024/7760264.pdf",
            "nomeFornecedor": "Equipe Negocios Imobiliarios - Luis E P Barbosa",
            "cnpjCpfFornecedor": "28798837000147",
            "valorLiquido": 3300.0,
            "valorGlosa": 0.0,
            "numRessarcimento": "",
            "codLote": 2052368,
            "parcela": 0
        },
        {
            "ano": 2024,
            "mes": 3,
            "tipoDespesa": "MANUTENÇÃO DE ESCRITÓRIO DE APOIO À ATIVIDADE PARLAMENTAR",
            "codDocumento": 7705878,
            "tipoDocumento": "Recibos/Outros",
            "codTipoDocumento": 1,
            "dataDocumento": "2024-03-10",
            "numDocumento": "S/N",
            "valorDocumento": 3300.0,
            "urlDocumento": "https://www.camara.leg.br/cota-parlamentar/documentos/publ/3516/2024/7705878.pdf",
            "nomeFornecedor": "Equipe Negocios Imobiliarios - Luis E P Barbosa",
            "cnpjCpfFornecedor": "28798837000147",
            "valorLiquido": 3300.0,
            "valorGlosa": 0.0,
            "numRessarcimento": "",
            "codLote": 2023284,
            "parcela": 0
        },
        {
            "ano": 2024,
            "mes": 6,
            "tipoDespesa": "MANUTENÇÃO DE ESCRITÓRIO DE APOIO À ATIVIDADE PARLAMENTAR",
            "codDocumento": 7785115,
            "tipoDocumento": "Recibos/Outros",
            "codTipoDocumento": 1,
            "dataDocumento": "2024-06-10",
            "numDocumento": "s/n",
            "valorDocumento": 3300.0,
            "urlDocumento": "https://www.camara.leg.br/cota-parlamentar/documentos/publ/3516/2024/7785115.pdf",
            "nomeFornecedor": "Equipe Negocios Imobiliarios - Luis E P Barbosa",
            "cnpjCpfFornecedor": "28798837000147",
            "valorLiquido": 3300.0,
            "valorGlosa": 0.0,
            "numRessarcimento": "",
            "codLote": 2064849,
            "parcela": 0
        },
        {
            "ano": 2024,
            "mes": 7,
            "tipoDespesa": "MANUTENÇÃO DE ESCRITÓRIO DE APOIO À ATIVIDADE PARLAMENTAR",
            "codDocumento": 7783837,
            "tipoDocumento": "Recibos/Outros",
            "codTipoDocumento": 1,
            "dataDocumento": "2024-07-10",
            "numDocumento": "s/n",
            "valorDocumento": 3300.0,
            "urlDocumento": "https://www.camara.leg.br/cota-parlamentar/documentos/publ/3516/2024/7783837.pdf",
            "nomeFornecedor": "Equipe Negocios Imobiliarios - Luis E P Barbosa",
            "cnpjCpfFornecedor": "28798837000147",
            "valorLiquido": 3300.0,
            "valorGlosa": 0.0,
            "numRessarcimento": "",
            "codLote": 2064319,
            "parcela": 0
        },
        {
            "ano": 2024,
            "mes": 4,
            "tipoDespesa": "MANUTENÇÃO DE ESCRITÓRIO DE APOIO À ATIVIDADE PARLAMENTAR",
            "codDocumento": 7713445,
            "tipoDocumento": "Nota Fiscal",
            "codTipoDocumento": 0,
            "dataDocumento": "2024-04-03",
            "numDocumento": "00002738",
            "valorDocumento": 7291.2,
            "urlDocumento": "https://www.camara.leg.br/cota-parlamentar/documentos/publ/3516/2024/7713445.pdf",
            "nomeFornecedor": "VIZION GESTAO DE NEGOCIOS EMPRESARIAIS LTDA",
            "cnpjCpfFornecedor": "07979987000187",
            "valorLiquido": 7291.2,
            "valorGlosa": 0.0,
            "numRessarcimento": "",
            "codLote": 2027372,
            "parcela": 0
        },
        {
            "ano": 2024,
            "mes": 1,
            "tipoDespesa": "DIVULGAÇÃO DA ATIVIDADE PARLAMENTAR.",
            "codDocumento": 7698779,
            "tipoDocumento": "Nota Fiscal",
            "codTipoDocumento": 0,
            "dataDocumento": "2024-03-06",
            "numDocumento": "00001502",
            "valorDocumento": 2800.0,
            "urlDocumento": "https://www.camara.leg.br/cota-parlamentar/documentos/publ/3516/2024/7698779.pdf",
            "nomeFornecedor": "COMUNIQUE ASSESSORIA DE COMUNICAÇÃO LTDA.",
            "cnpjCpfFornecedor": "04269852000130",
            "valorLiquido": 2800.0,
            "valorGlosa": 0.0,
            "numRessarcimento": "",
            "codLote": 2019525,
            "parcela": 0
        },
        {
            "ano": 2024,
            "mes": 2,
            "tipoDespesa": "DIVULGAÇÃO DA ATIVIDADE PARLAMENTAR.",
            "codDocumento": 7698784,
            "tipoDocumento": "Nota Fiscal",
            "codTipoDocumento": 0,
            "dataDocumento": "2024-03-06",
            "numDocumento": "00001503",
            "valorDocumento": 2800.0,
            "urlDocumento": "https://www.camara.leg.br/cota-parlamentar/documentos/publ/3516/2024/7698784.pdf",
            "nomeFornecedor": "COMUNIQUE ASSESSORIA DE COMUNICAÇÃO LTDA.",
            "cnpjCpfFornecedor": "04269852000130",
            "valorLiquido": 2800.0,
            "valorGlosa": 0.0,
            "numRessarcimento": "",
            "codLote": 2019529,
            "parcela": 0
        },
        {
            "ano": 2024,
            "mes": 3,
            "tipoDespesa": "DIVULGAÇÃO DA ATIVIDADE PARLAMENTAR.",
            "codDocumento": 7735927,
            "tipoDocumento": "Nota Fiscal",
            "codTipoDocumento": 0,
            "dataDocumento": "2024-04-01",
            "numDocumento": "00001516",
            "valorDocumento": 2800.0,
            "urlDocumento": "https://www.camara.leg.br/cota-parlamentar/documentos/publ/3516/2024/7735927.pdf",
            "nomeFornecedor": "COMUNIQUE ASSESSORIA DE COMUNICAÇÃO LTDA.",
            "cnpjCpfFornecedor": "04269852000130",
            "valorLiquido": 2800.0,
            "valorGlosa": 0.0,
            "numRessarcimento": "",
            "codLote": 2039737,
            "parcela": 0
        },
        {
            "ano": 2024,
            "mes": 4,
            "tipoDespesa": "DIVULGAÇÃO DA ATIVIDADE PARLAMENTAR.",
            "codDocumento": 7735936,
            "tipoDocumento": "Nota Fiscal",
            "codTipoDocumento": 0,
            "dataDocumento": "2024-05-05",
            "numDocumento": "00001527",
            "valorDocumento": 2800.0,
            "urlDocumento": "https://www.camara.leg.br/cota-parlamentar/documentos/publ/3516/2024/7735936.pdf",
            "nomeFornecedor": "COMUNIQUE ASSESSORIA DE COMUNICAÇÃO LTDA.",
            "cnpjCpfFornecedor": "04269852000130",
            "valorLiquido": 2800.0,
            "valorGlosa": 0.0,
            "numRessarcimento": "",
            "codLote": 2039742,
            "parcela": 0
        },
        {
            "ano": 2024,
            "mes": 3,
            "tipoDespesa": "DIVULGAÇÃO DA ATIVIDADE PARLAMENTAR.",
            "codDocumento": 7712123,
            "tipoDocumento": "Nota Fiscal",
            "codTipoDocumento": 0,
            "dataDocumento": "2024-03-15",
            "numDocumento": "323",
            "valorDocumento": 1000.0,
            "urlDocumento": "https://www.camara.leg.br/cota-parlamentar/documentos/publ/3516/2024/7712123.pdf",
            "nomeFornecedor": "ELDORADO COMUNICACAO E JORNALISMO LTDA",
            "cnpjCpfFornecedor": "37894749000130",
            "valorLiquido": 1000.0,
            "valorGlosa": 0.0,
            "numRessarcimento": "",
            "codLote": 2026675,
            "parcela": 0
        },
        {
            "ano": 2024,
            "mes": 4,
            "tipoDespesa": "DIVULGAÇÃO DA ATIVIDADE PARLAMENTAR.",
            "codDocumento": 7726044,
            "tipoDocumento": "Nota Fiscal",
            "codTipoDocumento": 0,
            "dataDocumento": "2024-04-12",
            "numDocumento": "340",
            "valorDocumento": 1000.0,
            "urlDocumento": "https://www.camara.leg.br/cota-parlamentar/documentos/publ/3516/2024/7726044.pdf",
            "nomeFornecedor": "ELDORADO COMUNICACAO E JORNALISMO LTDA",
            "cnpjCpfFornecedor": "37894749000130",
            "valorLiquido": 1000.0,
            "valorGlosa": 0.0,
            "numRessarcimento": "",
            "codLote": 2034012,
            "parcela": 0
        }
    ],
    "links": [
        {
            "rel": "self",
            "href": "https://dadosabertos.camara.leg.br/api/v2/deputados/220686/despesas?ordem=ASC&ordenarPor=ano"
        },
        {
            "rel": "next",
            "href": "https://dadosabertos.camara.leg.br/api/v2/deputados/220686/despesas?ordem=ASC&ordenarPor=ano&pagina=2&itens=15"
        },
        {
            "rel": "first",
            "href": "https://dadosabertos.camara.leg.br/api/v2/deputados/220686/despesas?ordem=ASC&ordenarPor=ano&pagina=1&itens=15"
        },
        {
            "rel": "last",
            "href": "https://dadosabertos.camara.leg.br/api/v2/deputados/220686/despesas?ordem=ASC&ordenarPor=ano&pagina=3&itens=15"
        }
    ]
}