{
    "dados": [
        {
            "ano": 2024,
            "mes": 3,
            "tipoDespesa": "MANUTENÇÃO DE ESCRITÓRIO DE APOIO À ATIVIDADE PARLAMENTAR",
            "codDocumento": 7724478,
            "tipoDocumento": "Nota Fiscal",
            "codTipoDocumento": 0,
            "dataDocumento": "2024-03-07",
            "numDocumento": "1061",
            "valorDocumento": 575.4,
            "urlDocumento": "https://www.camara.leg.br/cota-parlamentar/documentos/publ/2430/2024/7724478.pdf",
            "nomeFornecedor": "AMORETTO CAFES EXPRESSO LTDA",
            "cnpjCpfFornecedor": "08532429000131",
            "valorLiquido": 575.4,
            "valorGlosa": 0.0,
            "numRessarcimento": "",
            "codLote": 2033207,
            "parcela": 0
        },
        {
            "ano": 2024,
            "mes": 4,
            "tipoDespesa": "MANUTENÇÃO DE ESCRITÓRIO DE APOIO À ATIVIDADE PARLAMENTAR",
            "codDocumento": 7726409,
            "tipoDocumento": "Nota Fiscal",
            "codTipoDocumento": 0,
            "dataDocumento": "2024-04-03",
            "numDocumento": "1147",
            "valorDocumento": 575.4,
            "urlDocumento": "https://www.camara.leg.br/cota-parlamentar/documentos/publ/2430/2024/7726409.pdf",
            "nomeFornecedor": "AMORETTO CAFES EXPRESSO LTDA",
            "cnpjCpfFornecedor": "08532429000131",
            "valorLiquido": 575.4,
            "valorGlosa": 0.0,
            "numRessarcimento": "",
            "codLote": 2034238,
            "parcela": 0
        },
        {
            "ano": 2024,
            "mes": 5,
            "tipoDespesa": "MANUTENÇÃO DE ESCRITÓRIO DE APOIO À ATIVIDADE PARLAMENTAR",
            "codDocumento": 7741254,
            "tipoDocumento": "Nota Fiscal",
            "codTipoDocumento": 0,
            "dataDocumento": "2024-05-07",
            "numDocumento": "1237",
            "valorDocumento": 575.4,
            "urlDocumento": "https://www.camara.leg.br/cota-parlamentar/documentos/publ/2430/2024/7741254.pdf",
            "nomeFornecedor": "AMORETTO CAFES EXPRESSO LTDA",
            "cnpjCpfFornecedor": "08532429000131",
            "valorLiquido": 575.4,
            "valorGlosa": 0.0,
            "numRessarcimento": "",
            "codLote": 2043060,
            "parcela": 0
        },
        {
            "ano": 2024,
            "mes": 6,
            "tipoDespesa": "MANUTENÇÃO DE ESCRITÓRIO DE APOIO À ATIVIDADE PARLAMENTAR",
            "codDocumento": 7758905,
            "tipoDocumento": "Nota Fiscal",
            "codTipoDocumento": 0,
            "dataDocumento": "2024-06-06",
            "numDocumento": "1324",
            "valorDocumento": 575.4,
            "urlDocumento": "https://www.camara.leg.br/cota-parlamentar/documentos/publ/2430/2024/7758905.pdf",
            "nomeFornecedor": "AMORETTO CAFES EXPRESSO LTDA",
            "cnpjCpfFornecedor": "08532429000131",
            "valorLiquido": 575.4,
            "valorGlosa": 0.0,
            "numRessarcimento": "",
            "codLote": 2051749,
            "parcela": 0
        },
        {
            "ano": 2024,
            "mes": 7,
            "tipoDespesa": "MANUTENÇÃO DE ESCRITÓRIO DE APOIO À ATIVIDADE PARLAMENTAR",
            "codDocumento": 7782216,
            "tipoDocumento": "Nota Fiscal",
            "codTipoDocumento": 0,
            "dataDocumento": "2024-07-03",
            "numDocumento": "1401",
            "valorDocumento": 575.4,
            "urlDocumento": "https://www.camara.leg.br/cota-parlamentar/documentos/publ/2430/2024/7782216.pdf",
            "nomeFornecedor": "AMORETTO CAFES EXPRESSO LTDA",
            "cnpjCpfFornecedor": "08532429000131",
            "valorLiquido": 575.4,
            "valorGlosa": 0.0,
            "numRessarcimento": "",
            "codLote": 2063436,
            "parcela": 0
        },
        {
            "ano": 2024,
            "mes": 3,
            "tipoDespesa": "MANUTENÇÃO DE ESCRITÓRIO DE APOIO À ATIVIDADE PARLAMENTAR",
            "codDocumento": 7717074,
            "tipoDocumento": "Nota Fiscal",
            "codTipoDocumento": 0,
            "dataDocumento": "2024-03-25",
            "numDocumento": "00000054",
            "valorDocumento": 3670.0,
            "urlDocumento": "https://www.camara.leg.br/cota-parlamentar/documentos/publ/2430/2024/7717074.pdf",
            "nomeFornecedor": "FERMED - IMPORTAÇÃO COMERCIO E MANUTENÇÃO DE EQUIP",
            "cnpjCpfFornecedor": "11399921000195",
            "valorLiquido": 3670.0,
            "valorGlosa": 0.0,
            "numRessarcimento": "",
            "codLote": 2029396,
            "parcela": 0
        },
        {
            "ano": 2024,
            "mes": 4,
            "tipoDespesa": "MANUTENÇÃO DE ESCRITÓRIO DE APOIO À ATIVIDADE PARLAMENTAR",
            "codDocumento": 7726425,
            "tipoDocumento": "Nota Fiscal",
            "codTipoDocumento": 0,
            "dataDocumento": "2024-04-26",
            "numDocumento": "00000055",
            "valorDocumento": 3670.0,
            "urlDocumento": "https://www.camara.leg.br/cota-parlamentar/documentos/publ/2430/2024/7726425.pdf",
            "nomeFornecedor": "FERMED - IMPORTAÇÃO COMERCIO E MANUTENÇÃO DE EQUIP",
            "cnpjCpfFornecedor": "11399921000195",
            "valorLiquido": 3670.0,
            "valorGlosa": 0.0,
            "numRessarcimento": "",
            "codLote": 2034239,
            "parcela": 0
        },
        {
            "ano": 2024,
            "mes": 5,
            "tipoDespesa": "MANUTENÇÃO DE ESCRITÓRIO DE APOIO À ATIVIDADE PARLAMENTAR",
            "codDocumento": 7742492,
            "tipoDocumento": "Nota Fiscal",
            "codTipoDocumento": 0,
            "dataDocumento": "2024-05-24",
            "numDocumento": "00000056",
            "valorDocumento": 3670.0,
            "urlDocumento": "https://www.camara.leg.br/cota-parlamentar/documentos/publ/2430/2024/7742492.pdf",
            "nomeFornecedor": "FERMED - IMPORTAÇÃO COMERCIO E MANUTENÇÃO DE EQUIP",
            "cnpjCpfFornecedor": "11399921000195",
            "valorLiquido": 3670.0,
            "valorGlosa": 0.0,
            "numRessarcimento": "",
            "codLote": 2043061,
            "parcela": 0
        },
        {
            "ano": 2024,
            "mes": 7,
            "tipoDespesa": "MANUTENÇÃO DE ESCRITÓRIO DE APOIO À ATIVIDADE PARLAMENTAR",
            "codDocumento": 7776191,
            "tipoDocumento": "Nota Fiscal",
            "codTipoDocumento": 0,
            "dataDocumento": "2024-07-26",
            "numDocumento": "00000058",
            "valorDocumento": 3670.0,
            "urlDocumento": "https://www.camara.leg.br/cota-parlamentar/documentos/publ/2430/2024/7776191.pdf",
            "nomeFornecedor": "FERMED - IMPORTAÇÃO COMERCIO E MANUTENÇÃO DE EQUIP",
            "cnpjCpfFornecedor": "11399921000195",
            "valorLiquido": 3670.0,
            "valorGlosa": 0.0,
            "numRessarcimento": "",
            "codLote": 2060484,
            "parcela": 0
        },
        {
            "ano": 2024,
            "mes": 6,
            "tipoDespesa": "MANUTENÇÃO DE ESCRITÓRIO DE APOIO À ATIVIDADE PARLAMENTAR",
            "codDocumento": 7759593,
            "tipoDocumento": "Nota Fiscal",
            "codTipoDocumento": 0,
            "dataDocumento": "2024-06-24",
            "numDocumento": "57",
            "valorDocumento": 3670.0,
            "urlDocumento": "https://www.camara.leg.br/cota-parlamentar/documentos/publ/2430/2024/7759593.pdf",
            "nomeFornecedor": "FERMED - IMPORTAÇÃO COMERCIO E MANUTENÇÃO DE EQUIP",
            "cnpjCpfFornecedor": "11399921000195",
            "valorLiquido": 3670.0,
            "valorGlosa": 0.0,
            "numRessarcimento": "",
            "codLote": 2052045,
            "parcela": 0
        },
        {
            "ano": 2024,
            "mes": 3,
            "tipoDespesa": "MANUTENÇÃO DE ESCRITÓRIO DE APOIO À ATIVIDADE PARLAMENTAR",
            "codDocumento": 7715426,
            "tipoDocumento": "Nota Fiscal",
            "codTipoDocumento": 0,
            "dataDocumento": "2024-03-14",
            "numDocumento": "375",
            "valorDocumento": 350.0,
            "urlDocumento": "https://www.camara.leg.br/cota-parlamentar/documentos/publ/2430/2024/7715426.pdf",
            "nomeFornecedor": "PARLANET WEB E TECNOLOGIA EIRELI",
            "cnpjCpfFornecedor": "31602730000196",
            "valorLiquido": 350.0,
            "valorGlosa": 0.0,
            "numRessarcimento": "",
            "codLote": 2029395,
            "parcela": 0
        },
        {
            "ano": 2024,
            "mes": 4,
            "tipoDespesa": "MANUTENÇÃO DE ESCRITÓRIO DE APOIO À ATIVIDADE PARLAMENTAR",
            "codDocumento": 7726418,
            "tipoDocumento": "Nota Fiscal",
            "codTipoDocumento": 0,
            "dataDocumento": "2024-04-15",
            "numDocumento": "410",
            "valorDocumento": 350.0,
            "urlDocumento": "https://www.camara.leg.br/cota-parlamentar/documentos/publ/2430/2024/7726418.pdf",
            "nomeFornecedor": "PARLANET WEB E TECNOLOGIA EIRELI",
            "cnpjCpfFornecedor": "31602730000196",
            "valorLiquido": 350.0,
            "valorGlosa": 0.0,
            "numRessarcimento": "",
            "codLote": 2034238,
            "parcela": 0
        },
        {
            "ano": 2024,
            "mes": 5,
            "tipoDespesa": "MANUTENÇÃO DE ESCRITÓRIO DE APOIO À ATIVIDADE PARLAMENTAR",
            "codDocumento": 7741250,
            "tipoDocumento": "Nota Fiscal",
            "codTipoDocumento": 0,
            "dataDocumento": "2024-05-16",
            "numDocumento": "442",
            "valorDocumento": 350.0,
            "urlDocumento": "https://www.camara.leg.br/cota-parlamentar/documentos/publ/2430/2024/7741250.pdf",
            "nomeFornecedor": "PARLANET WEB E TECNOLOGIA EIRELI",
            "cnpjCpfFornecedor": "31602730000196",
            "valorLiquido": 350.0,
            "valorGlosa": 0.0,
            "numRessarcimento": "",
            "codLote": 2043060,
            "parcela": 0
        },
        {
            "ano": 2024,
            "mes": 6,
            "tipoDespesa": "MANUTENÇÃO DE ESCRITÓRIO DE APOIO À ATIVIDADE PARLAMENTAR",
            "codDocumento": 7758895,
            "tipoDocumento": "Nota Fiscal",
            "codTipoDocumento": 0,
            "dataDocumento": "2024-06-17",
            "numDocumento": "472",
            "valorDocumento": 350.0,
            "urlDocumento": "https://www.camara.leg.br/cota-parlamentar/documentos/publ/2430/2024/7758895.pdf",
            "nomeFornecedor": "PARLANET WEB E TECNOLOGIA EIRELI",
            "cnpjCpfFornecedor": "31602730000196",
            "valorLiquido": 350.0,
            "valorGlosa": 0.0,
            "numRessarcimento": "",
            "codLote": 2051749,
            "parcela": 0
        },
        {
            "ano": 2024,
            "mes": 7,
            "tipoDespesa": "MANUTENÇÃO DE ESCRITÓRIO DE APOIO À ATIVIDADE PARLAMENTAR",
            "codDocumento": 7775596,
            "tipoDocumento": "Nota Fiscal",
            "codTipoDocumento": 0,
            "dataDocumento": "2024-07-17",
            "numDocumento": "503",
            "valorDocumento": 350.0,
            "urlDocumento": "https://www.camara.leg.br/cota-parlamentar/documentos/publ/2430/2024/7775596.pdf",
            "nomeFornecedor": "PARLANET WEB E TECNOLOGIA EIRELI",
            "cnpjCpfFornecedor": "31602730000196",
            "valorLiquido": 350.0,
            "valorGlosa": 0.0,
            "numRessarcimento": "",
            "codLote": 2060354,
            "parcela": 0
        }
    ],
    "links": [
        {
            "rel": "self",
            "href": "https://dadosabertos.camara.leg.br/api/v2/deputados/92776/despesas?ordem=ASC&ordenarPor=ano"
        },
        {
            "rel": "next",
            "href": "https://dadosabertos.camara.leg.br/api/v2/deputados/92776/despesas?ordem=ASC&ordenarPor=ano&pagina=2&itens=15"
        },
        {
            "rel": "first",
            "href": "https://dadosabertos.camara.leg.br/api/v2/deputados/92776/despesas?ordem=ASC&ordenarPor=ano&pagina=1&itens=15"
        },
        {
            "rel": "last",
            "href": "https://dadosabertos.camara.leg.br/api/v2/deputados/92776/despesas?ordem=ASC&ordenarPor=ano&pagina=10&itens=15"
        }
    ]
}